{
  "welcomeMessage": "Bienvenue dans l'EMR de l'Hôpital Universitaire de Mirebalais",

    "country": "HAITI",
    "site": "MIREBALAIS",

  "components": [
        "visitManagement",
        "activeVisits",
        "checkIn",
        "checkInHomepageApp",
        "vitals",
        "consult",
        "edConsult",
        "adt",
        "deathCertificate",
        "radiology",
        "dispensing",
        "surgery",
        "overviewReports",
        "dataExports",
        "archives",
        "wristbands",
        "appointmentScheduling",
        "systemAdministration",
        "managePrinters",
        "myAccount",
        "legacyMpi",
        "legacyPatientRegistration",
        "lacollinePatientRegistrationEncounterTypes",
        "managePrinters",
        "idcardPrinting"
  ],

  "globalProperties": {
        "mirebalais.checkIn.paymentAmounts": "50,0",
        "mirebalais.checkIn.paymentAmountLabels": "50,Exempt",
        "mirebalais.checkIn.paymentAmountDefault": "50"
  },

  "scheduleBackupReports": "false",

  "registrationConfig": {
    "allowUnknownPatients": true,
    "allowManualEntryOfPrimaryIdentifier": true
  }
}